{
    "/js/app.js": "/js/app.js?id=fb29158d11b0b7508636",
    "/css/app.css": "/css/app.css?id=832a56db213306ac740e",
    "/css/auth.css": "/css/auth.css?id=452a002710d80b3af4cb",
    "/js/app.js.map": "/js/app.js.map?id=482be7688e7b55560b3c",
    "/css/app.css.map": "/css/app.css.map?id=099799f74a88bd02d491",
    "/css/auth.css.map": "/css/auth.css.map?id=15b67aad97faa5b1a985",
    "/js/vendor.js": "/js/vendor.js?id=1dd22d0981d6330a3046",
    "/js/vendor.js.map": "/js/vendor.js.map?id=c2643acf7bea1d3247b7",
    "/js/manifest.js": "/js/manifest.js?id=d64713044d4b02b1808b",
    "/js/manifest.js.map": "/js/manifest.js.map?id=2ca5d8e27519e1d06c03"
}
